.coveragerc
.flake8
.pylintrc
LICENSE
MANIFEST.in
README.rst
pyproject.toml
setup.py
tox.ini
fellowship/__init__.py
fellowship/_arg_parser.py
fellowship/_version.py
fellowship/cli.py
fellowship/contract.py
fellowship/contract_generator.py
fellowship/contract_renderer.py
fellowship/endpoint_tester.py
fellowship/grpc_generator.py
fellowship/grpc_tester.py
fellowship/reporter.py
fellowship/rest_tester.py
fellowship/strict_schema_builder.py
fellowship/utilis.py
fellowship.egg-info/PKG-INFO
fellowship.egg-info/SOURCES.txt
fellowship.egg-info/dependency_links.txt
fellowship.egg-info/entry_points.txt
fellowship.egg-info/requires.txt
fellowship.egg-info/top_level.txt
fellowship/configs/grpc_config.yaml
fellowship/configs/rest_config.yaml
fellowship/schemas/grpc_schema.json
fellowship/schemas/rest_schema.json