Metadata-Version: 2.1
Name: fellowship
Version: 0.1.0
Summary: Library for testing api endpoints 
Home-page: https://github.com/nokia/contract-test-framework
Author: Robin Nyman
Author-email: robin.nyman@nokia.com
License: BSD-3-Clause
Keywords: Microservice Contract Testing
Platform: UNKNOWN
Classifier: Intended Audience :: Developers
Classifier: License :: OSI Approved :: BSD License
Classifier: Operating System :: OS Independent
Classifier: Programming Language :: Python :: 3
Classifier: Programming Language :: Python :: 3.6
Classifier: Programming Language :: Python :: 3.7
Classifier: Programming Language :: Python :: 3.8
Classifier: Programming Language :: Python :: 3.9
Classifier: Topic :: Software Development :: Testing
License-File: LICENSE
